{
    "variants": {
        "facing=north": {
            "model": "destroy:block/blowpipe"
        },
        "facing=south": {
            "model": "destroy:block/blowpipe",
            "y": 180
        },
        "facing=east": {
            "model": "destroy:block/blowpipe",
            "y": 90
        },
        "facing=west": {
            "model": "destroy:block/blowpipe",
            "y": 270
        },
        "facing=up": {
            "model": "destroy:block/blowpipe",
            "x": 270
        },
        "facing=down": {
            "model": "destroy:block/blowpipe",
            "x": 90
        }
    }
}